reagle/__init__.py
reagle/functions - Copy.py
reagle/functions.py
reagle-0.2.0.dist-info/DESCRIPTION.rst
reagle-0.2.0.dist-info/METADATA
reagle-0.2.0.dist-info/RECORD
reagle-0.2.0.dist-info/WHEEL
reagle-0.2.0.dist-info/metadata.json
reagle-0.2.0.dist-info/top_level.txt
