Metadata-Version: 2.0
Name: reagle
Version: 0.2.0
Summary: For creating data visualisations from EAGLE snapshots
Home-page: https://github.com/Alex-Tremayne/reagle
Author: Alex Tremayne
Author-email: alexjtremayne@gmail.com
License: MIT
Platform: UNKNOWN
Classifier: Development Status :: 3 - Alpha
Classifier: License :: OSI Approved :: MIT License
Classifier: Programming Language :: Python :: 3.6
Requires-Dist: numpy
Requires-Dist: h5py
